ss_utils_logging/__init__.py
ss_utils_logging/cli.py
ss_utils_logging/common.py
ss_utils_logging/formatters.py
ss_utils_logging/logging_config.py
ss_utils_logging/example_config/logging.prod.yaml
ss_utils_logging/example_config/logging.yaml
ss_utils_logging-0.0.11.dist-info/METADATA
ss_utils_logging-0.0.11.dist-info/WHEEL
ss_utils_logging-0.0.11.dist-info/entry_points.txt
ss_utils_logging-0.0.11.dist-info/licenses/LICENSE
ss_utils_logging-0.0.11.dist-info/RECORD
