Metadata-Version: 2.4
Name: ss-utils-logging
Version: 0.0.11
Summary: Utilities for logging with orjson serialization and advanced features
Project-URL: Homepage, https://github.com/shern2/ss-utils-logging
Project-URL: Repository, https://github.com/shern2/ss-utils-logging
Project-URL: Issues, https://github.com/shern2/ss-utils-logging/issues
Author: shern
License: MIT
License-File: LICENSE
Keywords: configuration,logging,orjson,yaml
Requires-Python: >=3.10
Requires-Dist: orjson>=3.11.0
Requires-Dist: pyyaml>=6.0.2
Requires-Dist: typer-slim[standard]>=0.16.0
